alibabacloud_ddospro20170725/__init__.py
alibabacloud_ddospro20170725/client.py
alibabacloud_ddospro20170725/models.py
alibabacloud_ddospro20170725-1.0.0.dist-info/LICENSE
alibabacloud_ddospro20170725-1.0.0.dist-info/METADATA
alibabacloud_ddospro20170725-1.0.0.dist-info/WHEEL
alibabacloud_ddospro20170725-1.0.0.dist-info/top_level.txt
alibabacloud_ddospro20170725-1.0.0.dist-info/RECORD
